PYMD/NOTICE
PYMD/__init__.py
PYMD/__main__.py
PYMD/_pymd.py
PYMD/OSL/LICENSE_MARKITDOWN
PYMD/OSL/LICENSE_PYSIDE6
PYMD/OSL/url_licenses.srm
PYMD/database/Manager.py
PYMD/database/__init__.py
PYMD/interface/__init__.py
PYMD/interface/_about.py
PYMD/interface/_initialHelp.py
PYMD/interface/_interface.py
PYMD/interface/_lang.py
PYMD/interface/_osl.py
PYMD/interface/resources_rc.py
PYMD/interface/ui_dialog_about.py
PYMD/interface/ui_dialog_language.py
PYMD/interface/ui_main_window.py
PYMD/interface/ui_osl.py
PYMD/interface/assets/img/gh-logo.png
PYMD/interface/assets/img/me.webp
PYMD/interface/assets/img/osl_icon.webp
PYMD/interface/assets/img/language/en_GB.svg
PYMD/interface/assets/img/language/es_CO.svg
PYMD/interface/assets/img/logo-pymd/logo-pymd-1.png
PYMD/interface/assets/img/logo-pymd/logo-pymd-2.1.png
PYMD/interface/assets/img/logo-pymd/logo-pymd-2.2.png
PYMD/interface/assets/img/logo-pymd/logo-pymd-2.png
PYMD/interface/assets/img/logo-pymd/logo-pymd-3.png
PYMD/interface/assets/img/logo-pymd/logo-pymd-4.png
PYMD/interface/assets/img/logo-pymd/logo-pymd-5.png
PYMD/interface/translations/locale/pymd_en_GB.qm
PYMD/interface/translations/locale/pymd_en_GB.ts
PYMD/interface/translations/locale/pymd_es_CO.qm
PYMD/interface/translations/locale/pymd_es_CO.ts
PYMD/interface/translations/others/ABOUT_en_GB.trg
PYMD/interface/translations/others/ABOUT_es_CO.trg
PYMD/interface/translations/others/IH_en_GB.srm
PYMD/interface/translations/others/IH_es_CO.srm
PYMD/interface/translations/others/NOTICE_en_GB.srm
PYMD/interface/translations/others/NOTICE_es_CO.srm
PYMD/logic/Converter.py
PYMD/logic/__init__.py
PYMD/logs/__init__.py
PYMD/models/Returning.py
PYMD/models/__init__.py
PYMD/utils/FilesManager.py
PYMD/utils/__init__.py
test_pymd-0.1.8.dist-info/licenses/LICENSE
test_pymd-0.1.8.dist-info/METADATA
test_pymd-0.1.8.dist-info/WHEEL
test_pymd-0.1.8.dist-info/entry_points.txt
test_pymd-0.1.8.dist-info/top_level.txt
test_pymd-0.1.8.dist-info/RECORD
