Metadata-Version: 2.4
Name: test-pymd
Version: 0.1.8
Summary: Python GUI to convert a wide variety of files to Markdown format
Author-email: abascas <a@gmail.com>
License: MIT License
Project-URL: Homepage, https://github.com/testing/test
Project-URL: Repository, https://github.com/testing/test
Project-URL: Issues, https://github.com/testing/test/issues
Classifier: Development Status :: 3 - Alpha
Classifier: Intended Audience :: End Users/Desktop
Classifier: Intended Audience :: Developers
Classifier: Topic :: Utilities
Classifier: Topic :: Text Processing :: Markup
Classifier: License :: OSI Approved :: MIT License
Classifier: Programming Language :: Python :: 3.7
Classifier: Programming Language :: Python :: 3.8
Classifier: Programming Language :: Python :: 3.9
Classifier: Programming Language :: Python :: 3.10
Classifier: Programming Language :: Python :: 3.11
Classifier: Programming Language :: Python :: 3.12
Classifier: Operating System :: OS Independent
Classifier: Environment :: X11 Applications :: Qt
Classifier: Environment :: Win32 (MS Windows)
Classifier: Environment :: MacOS X
Requires-Python: >=3.7
License-File: LICENSE
Requires-Dist: markitdown[all]==0.1.1
Requires-Dist: chromologger==0.1.8
Requires-Dist: PySide6==6.9.0
Requires-Dist: sqlazo==0.1.5
Requires-Dist: chromolog==0.2.4
Dynamic: license-file
